KickZero/__init__.py
kickzero-1.1.0.dist-info/licenses/LICENSE
kickzero-1.1.0.dist-info/METADATA
kickzero-1.1.0.dist-info/WHEEL
kickzero-1.1.0.dist-info/top_level.txt
kickzero-1.1.0.dist-info/RECORD
