Metadata-Version: 2.4
Name: KickZero
Version: 1.1.0
Summary: Kick.com için gelişmiş ve kolay kullanımlı bot framework'ü
Home-page: https://github.com/SeymenSozen/KickZero
Author: Seymen Sözen
Classifier: Programming Language :: Python :: 3
Classifier: License :: OSI Approved :: MIT License
Classifier: Operating System :: OS Independent
Requires-Python: >=3.8
License-File: LICENSE
Requires-Dist: aiohttp
Requires-Dist: websockets
Requires-Dist: colorama
Dynamic: author
Dynamic: classifier
Dynamic: description
Dynamic: description-content-type
Dynamic: home-page
Dynamic: license-file
Dynamic: requires-dist
Dynamic: requires-python
Dynamic: summary
